profila/__init__.py
profila/__main__.py
profila/_gdb.py
profila/_ipython.py
profila/_render.py
profila/_stats.py
profila-0.3.2.dist-info/LICENSE
profila-0.3.2.dist-info/METADATA
profila-0.3.2.dist-info/WHEEL
profila-0.3.2.dist-info/top_level.txt
profila-0.3.2.dist-info/RECORD
