Metadata-Version: 2.2
Name: profila
Version: 0.3.2
Summary: A profiler for Numba
Author: Itamar Turner-Trauring
License: Apache-2.0
Project-URL: Homepage, https://github.com/pythonspeed/profila
Project-URL: Issues, https://github.com/pythonspeed/profila/issues
Project-URL: CI, https://github.com/pythonspeed/profila/actions
Classifier: License :: OSI Approved :: Apache Software License
Requires-Python: >=3.9
License-File: LICENSE
Requires-Dist: pygdbmi
Provides-Extra: test
Requires-Dist: pytest; extra == "test"
Requires-Dist: ruff; extra == "test"
Requires-Dist: numba; extra == "test"
Requires-Dist: mypy; extra == "test"
Requires-Dist: hypothesis; extra == "test"
Requires-Dist: syrupy; extra == "test"
Requires-Dist: nbconvert; extra == "test"
Requires-Dist: ipykernel; extra == "test"
